Metadata-Version: 2.1
Name: buscemizer
Version: 0.0.0
Summary: Add Steve Buscemi's beautiful facial features to facial photos!
Home-page: https://github.com/nklapste/buscemizer
Author: Nathan Douglas Klapstein
Author-email: nklapste@ualberta.ca
License: MIT
Download-URL: https://github.com/nklapste/buscemizer/archive/master.zip
Platform: UNKNOWN
Classifier: Environment :: Console
Classifier: License :: OSI Approved :: MIT License
Classifier: Programming Language :: Python :: 3
Classifier: Programming Language :: Python :: 3.5
Classifier: Programming Language :: Python :: 3.6
Provides-Extra: docs
